Metadata-Version: 2.1
Name: odoo14-addon-l10n_it_declaration_of_intent
Version: 14.0.1.4.1
Summary: Gestione dichiarazioni di intento
Home-page: https://github.com/OCA/l10n-italy
Author: Francesco Apruzzese, Sergio Corato, Glauco Prina, Lara Baggio, Odoo Community Association (OCA)
Author-email: support@odoo-community.org
License: AGPL-3
Classifier: Programming Language :: Python
Classifier: Framework :: Odoo
Classifier: Framework :: Odoo :: 14.0
Classifier: License :: OSI Approved :: GNU Affero General Public License v3
Requires-Python: >=3.6
Requires-Dist: odoo<14.1dev,>=14.0a
